confidence_interval_estimator_ML/init.py
confidence_interval_estimator_ML/utils.py
confidence_interval_estimator_ML-0.1.2.dist-info/LICENSE
confidence_interval_estimator_ML-0.1.2.dist-info/METADATA
confidence_interval_estimator_ML-0.1.2.dist-info/WHEEL
confidence_interval_estimator_ML-0.1.2.dist-info/top_level.txt
confidence_interval_estimator_ML-0.1.2.dist-info/RECORD
