Metadata-Version: 2.1
Name: confidence-interval-estimator-ML
Version: 0.1.2
Summary: UNKNOWN
Home-page: https://github.com/user/confidence_interval_estimator_ML
Author: Giovanni Ciampi
Author-email: giovanniciampi95@gmail.com
License: GNU General Public License (GPL)
Download-URL: https://github.com/GiovanniCiampi/confidence_interval_estimator_ML/archive/v0.1.2.tar.gz
Keywords: Confidence-Intervals,Confidence,Machine Learning,Accuracy,Bootstrap,MonteCarlo,Machine-Learning
Platform: UNKNOWN
Classifier: Development Status :: 4 - Beta
Classifier: Intended Audience :: Developers
Classifier: Topic :: Software Development :: Build Tools
Classifier: License :: OSI Approved :: GNU General Public License (GPL)
Classifier: Programming Language :: Python :: 3.4
Classifier: Programming Language :: Python :: 3.5
Classifier: Programming Language :: Python :: 3.6
Requires-Dist: tqdm
Requires-Dist: numpy
Requires-Dist: scipy
Requires-Dist: matplotlib
